sanic_brogz/__init__.py
sanic_brogz-0.1.3.dist-info/LICENSE
sanic_brogz-0.1.3.dist-info/METADATA
sanic_brogz-0.1.3.dist-info/WHEEL
sanic_brogz-0.1.3.dist-info/top_level.txt
sanic_brogz-0.1.3.dist-info/RECORD
