Metadata-Version: 2.1
Name: sanic-brogz
Version: 0.1.3
Summary: An extension which allows you to easily brotli compress or gzip your Sanic responses.
Home-page: http://github.com/bitpartio/sanic_brogz
Author: Michael Chisari
Author-email: UNKNOWN
License: MIT
Keywords: sanic,gzip,brotli
Platform: UNKNOWN
Classifier: Programming Language :: Python :: 3.5
Classifier: Programming Language :: Python :: 3.6
Classifier: Programming Language :: Python :: 3 :: Only
Classifier: Topic :: Internet :: WWW/HTTP :: Session
Requires-Dist: sanic
Requires-Dist: brotli
